{"commitInfo":{"timestamp":1780725066541,"operation":"WRITE","operationParameters":{"mode":"Append"},"engineInfo":"delta-rs:py-1.6.0","operationMetrics":{"execution_time_ms":2,"num_added_files":1,"num_added_rows":10,"num_partitions":0,"num_removed_files":0},"clientVersion":"delta-rs.py-1.6.0"}}
{"add":{"path":"part-00000-7aee0949-34bf-4071-9559-65413de1cf78-c000.snappy.parquet","partitionValues":{},"size":8202,"modificationTime":1780725066541,"dataChange":true,"stats":"{\"numRecords\":10,\"minValues\":{\"absolute_magnitude_h\":18.59,\"close_approach_date\":\"2021-05-31T00:00:00Z\",\"is_potentially_hazardous\":false,\"close_approach_datetime\":\"2021-05-31T03:27:00Z\",\"size_class\":\"medium\",\"date\":\"2021-05-31T00:00:00Z\",\"hazard_label\":\"high\",\"is_named\":false,\"miss_distance_lunar\":2.9032247892,\"miss_distance_percentile\":0.3,\"id\":\"3530350\",\"critical_alert\":false,\"hash_id\":\"2003aee02d6cd3d8fd1eaa5837999aae\",\"hazard_score\":0.99,\"name\":\"(2010 MB)\",\"is_sentry_object\":false,\"diameter_km_avg\":0.026887016700000002,\"velocity_km_per_s\":3.4165750877,\"size_percentile\":21.3,\"nasa_jpl_url\":\"https://ssd.jpl.nasa.gov/tools/sbdb_lookup.html#/?sstr=3530350\",\"velocity_percentile\":2.4},\"maxValues\":{\"date\":\"2021-06-01T00:00:00Z\",\"is_potentially_hazardous\":true,\"velocity_percentile\":92.2,\"hazard_score\":0.99,\"size_class\":\"small\",\"miss_distance_lunar\":181.6813877966,\"close_approach_date\":\"2021-06-01T00:00:00Z\",\"close_approach_datetime\":\"2021-06-01T19:33:00Z\",\"diameter_km_avg\":0.82327061965,\"miss_distance_percentile\":92.0,\"size_percentile\":96.9,\"hash_id\":\"ef80305d3949211fa0d0ebd7133e8daa\",\"id\":\"3825059\",\"name\":\"(2018 LB)\",\"velocity_km_per_s\":24.4767717032,\"nasa_jpl_url\":\"https://ssd.jpl.nasa.gov/tools/sbdb_lookup.html#/?sstr=3825059\",\"critical_alert\":false,\"is_named\":false,\"is_sentry_object\":true,\"hazard_label\":\"moderate\",\"absolute_magnitude_h\":26.02},\"nullCount\":{\"velocity_percentile\":0,\"miss_distance_lunar\":0,\"is_named\":0,\"critical_alert\":0,\"diameter_km_avg\":0,\"name\":0,\"is_sentry_object\":0,\"nasa_jpl_url\":0,\"hash_id\":0,\"is_potentially_hazardous\":0,\"hazard_score\":0,\"size_percentile\":0,\"miss_distance_percentile\":0,\"date\":0,\"close_approach_datetime\":0,\"hazard_label\":0,\"id\":0,\"velocity_km_per_s\":0,\"close_approach_date\":0,\"size_class\":0,\"absolute_magnitude_h\":0}}","tags":null,"baseRowId":null,"defaultRowCommitVersion":null,"clusteringProvider":null}}